src/__init__.py
src/core.py
src/cli/cli.py
src/config/__init__.py
src/config/engine.py
src/config/loader.py
src/config/models.py
src/detectors/__init__.py
src/detectors/base.py
src/detectors/field_name_detector.py
src/detectors/manager.py
src/detectors/regex_detector.py
src/strategies/__init__.py
src/strategies/base.py
src/strategies/encrypt_strategy.py
src/strategies/hash_strategy.py
src/strategies/manager.py
src/strategies/mask_strategy.py
src/strategies/randomize_strategy.py
privacy_guard-0.1.0.dist-info/METADATA
privacy_guard-0.1.0.dist-info/WHEEL
privacy_guard-0.1.0.dist-info/entry_points.txt
privacy_guard-0.1.0.dist-info/RECORD
